hubway/LICENSE
hubway/__init__.py
hubway/__main__.py
hubway/version.py
hubway/host/__init__.py
hubway/host/main_host.py
hubway/host/publishing_host.py
hubway/misc/__init__.py
hubway/misc/default_shared_data.json
hubway/misc/my_theme.py
hubway/view/__init__.py
hubway/view/auth_view.py
hubway/view/central_view.py
hubway/view/failure_view.py
hubway/view/footer_view.py
hubway/view/header_view.py
hubway/view/main_view.py
hubway/view/node_view.py
hubway/view/publishing_view.py
hubway/view/tree_hook.py
tests/__init__.py
hubway-0.0.9.dist-info/LICENSE
hubway-0.0.9.dist-info/METADATA
hubway-0.0.9.dist-info/WHEEL
hubway-0.0.9.dist-info/entry_points.txt
hubway-0.0.9.dist-info/top_level.txt
hubway-0.0.9.dist-info/RECORD
