Metadata-Version: 2.1
Name: hubway
Version: 0.0.9
Summary: A Pyrustic tool to publish Python desktop app to Github
Home-page: https://github.com/pyrustic/hubway
Author: Pyrustic Evangelist
Author-email: pyrustic@protonmail.com
Maintainer: Pyrustic Evangelist
Maintainer-email: pyrustic@protonmail.com
License: MIT
Keywords: pyrustic-tool,software-distribution,desktop-application
Platform: UNKNOWN
Classifier: Programming Language :: Python :: 3
Classifier: License :: OSI Approved :: MIT License
Classifier: Operating System :: OS Independent
Requires-Python: >=3.5
Requires-Dist: pyrustic
